MANIFEST.in
MIT-LICENSE.txt
README.md
setup.py
twitterspawn/__init__.py
twitterspawn/base.py
twitterspawn/tasks.py
twitterspawn/throttle.py
twitterspawn/worker.py
twitterspawn.egg-info/PKG-INFO
twitterspawn.egg-info/SOURCES.txt
twitterspawn.egg-info/dependency_links.txt
twitterspawn.egg-info/not-zip-safe
twitterspawn.egg-info/requires.txt
twitterspawn.egg-info/top_level.txt