Metadata-Version: 1.0
Name: twitterspawn
Version: 0.1.3
Summary: Scalable, concurrent requests to the Twitter REST API, that respect Twitter's rate limits, using gevent and requests.
Home-page: https://github.com/swinton/twitterspawn
Author: Steve Winton
Author-email: stevewinton@gmail.com
License: MIT
Keywords: requests,python-requests,gevent,twitterspawn
Platform: UNKNOWN
Classifier: Development Status :: 4 - Beta
Classifier: Intended Audience :: Developers
Classifier: Programming Language :: Python
Classifier: License :: OSI Approved :: BSD License
Classifier: Operating System :: OS Independent
Classifier: Topic :: Internet :: WWW/HTTP
Classifier: Topic :: Software Development :: Libraries :: Python Modules
